opendisplay/__init__.py
opendisplay/device.py
opendisplay/discovery.py
opendisplay/exceptions.py
opendisplay/encoding/__init__.py
opendisplay/encoding/bitplanes.py
opendisplay/encoding/compression.py
opendisplay/encoding/dithering.py
opendisplay/encoding/images.py
opendisplay/models/__init__.py
opendisplay/models/advertisement.py
opendisplay/models/capabilities.py
opendisplay/models/config.py
opendisplay/models/enums.py
opendisplay/models/firmware.py
opendisplay/protocol/__init__.py
opendisplay/protocol/commands.py
opendisplay/protocol/config_parser.py
opendisplay/protocol/responses.py
opendisplay/transport/__init__.py
opendisplay/transport/connection.py
py_opendisplay-0.3.0.dist-info/METADATA
py_opendisplay-0.3.0.dist-info/WHEEL
py_opendisplay-0.3.0.dist-info/licenses/LICENSE
py_opendisplay-0.3.0.dist-info/RECORD
